git_debranch/__init__.py
git_debranch/console_scripts.py
git_debranch/loader.py
git_debranch/runner.py
git_debranch/script_engine.py
git_debranch/workflow.py
git_debranch/bpmn/process_group.json
git_debranch/bpmn/git-debranch/all_branches.bpmn
git_debranch/bpmn/git-debranch/branch_parser.bpmn
git_debranch/bpmn/git-debranch/confirm_deletion.json
git_debranch/bpmn/git-debranch/delete_branches.bpmn
git_debranch/bpmn/git-debranch/deletion_prompt.bpmn
git_debranch/bpmn/git-debranch/git-debranch.bpmn
git_debranch/bpmn/git-debranch/process_model.json
git_debranch/bpmn/git-debranch/spawn.bpmn
git_debranch-0.1.9.dist-info/LICENSE
git_debranch-0.1.9.dist-info/METADATA
git_debranch-0.1.9.dist-info/WHEEL
git_debranch-0.1.9.dist-info/entry_points.txt
git_debranch-0.1.9.dist-info/top_level.txt
git_debranch-0.1.9.dist-info/RECORD
