Metadata-Version: 2.1
Name: git-debranch
Version: 0.1.9
Summary: Remove git branches
Author: Jon Herron
Author-email: jon.herron@yahoo.com
License: lGPLv2
Requires-Python: >=3.9
License-File: LICENSE
Requires-Dist: SpiffWorkflow ==3.0.0rc2
